MANIFEST.in
README.txt
experimental.pietimemenu-configure.zcml
setup.cfg
setup.py
docs/HISTORY.txt
docs/INSTALL.txt
docs/LICENSE.GPL
docs/LICENSE.txt
experimental/__init__.py
experimental.pietimemenu.egg-info/PKG-INFO
experimental.pietimemenu.egg-info/SOURCES.txt
experimental.pietimemenu.egg-info/dependency_links.txt
experimental.pietimemenu.egg-info/entry_points.txt
experimental.pietimemenu.egg-info/namespace_packages.txt
experimental.pietimemenu.egg-info/not-zip-safe
experimental.pietimemenu.egg-info/paster_plugins.txt
experimental.pietimemenu.egg-info/requires.txt
experimental.pietimemenu.egg-info/top_level.txt
experimental/pietimemenu/__init__.py
experimental/pietimemenu/configure.zcml
experimental/pietimemenu/profiles.zcml
experimental/pietimemenu/setuphandlers.py
experimental/pietimemenu/skins.zcml
experimental/pietimemenu/tests.py
experimental/pietimemenu/version.txt
experimental/pietimemenu/browser/__init__.py
experimental/pietimemenu/browser/configure.zcml
experimental/pietimemenu/browser/interfaces.py
experimental/pietimemenu/browser/viewlet.pt
experimental/pietimemenu/browser/viewlets.py
experimental/pietimemenu/browser/images/README.txt
experimental/pietimemenu/browser/stylesheets/README.txt
experimental/pietimemenu/browser/stylesheets/main.css
experimental/pietimemenu/locales/README.txt
experimental/pietimemenu/profiles/default/cssregistry.xml
experimental/pietimemenu/profiles/default/experimental.pietimemenu_various.txt
experimental/pietimemenu/profiles/default/jsregistry.xml
experimental/pietimemenu/profiles/default/metadata.xml
experimental/pietimemenu/profiles/default/skins.xml
experimental/pietimemenu/profiles/default/viewlets.xml
experimental/pietimemenu/skins/experimental_pietimemenu_custom_images/CONTENT.txt
experimental/pietimemenu/skins/experimental_pietimemenu_js/CONTENT.txt
experimental/pietimemenu/skins/experimental_pietimemenu_js/jquery.pieselmenue.js
experimental/pietimemenu/skins/experimental_pietimemenu_styles/pieselmenu.css