Metadata-Version: 1.0
Name: experimental.pietimemenu
Version: 0.1
Summary: Experimental Radial (Pie) Menu for time input
Home-page: http://svn.plone.org/svn/collective/experimental.pietimemenu/
Author: Christian Ledermann
Author-email: christian.ledermann@gmail.com
License: GPL
Platform: UNKNOWN
Classifier: Framework :: Plone
Classifier: Framework :: Plone :: 4.0
Classifier: Framework :: Plone :: 4.1
Classifier: Intended Audience :: Developers
Classifier: Programming Language :: Python
Classifier: License :: OSI Approved :: GNU General Public License (GPL)
